{
  "updated": "Tue 23 Jun 2026, 09:25 CEST",
  "timezone": "Europe/Berlin",
  "matches": [
    {
      "home": "Portugal",
      "away": "Uzbekistan",
      "kickoff": "Tue 23 Jun, 19:00",
      "day": "Today",
      "sort_key": "202606231900",
      "method": "market",
      "n_books": 1,
      "exp_goals_home": 2.88,
      "exp_goals_away": 0.63,
      "p_home": 0.808,
      "p_draw": 0.124,
      "p_away": 0.067,
      "predictions": [
        {
          "score": "2:0",
          "points": "1.95"
        },
        {
          "score": "3:0",
          "points": "1.91"
        },
        {
          "score": "3:1",
          "points": "1.89"
        }
      ]
    },
    {
      "home": "England",
      "away": "Ghana",
      "kickoff": "Tue 23 Jun, 22:00",
      "day": "Today",
      "sort_key": "202606232200",
      "method": "market",
      "n_books": 1,
      "exp_goals_home": 2.63,
      "exp_goals_away": 0.67,
      "p_home": 0.762,
      "p_draw": 0.141,
      "p_away": 0.097,
      "predictions": [
        {
          "score": "2:0",
          "points": "1.86"
        },
        {
          "score": "1:0",
          "points": "1.80"
        },
        {
          "score": "3:1",
          "points": "1.80"
        }
      ]
    },
    {
      "home": "Panama",
      "away": "Croatia",
      "kickoff": "Wed 24 Jun, 01:00",
      "day": "Tomorrow",
      "sort_key": "202606240100",
      "method": "market",
      "n_books": 1,
      "exp_goals_home": 0.97,
      "exp_goals_away": 2.19,
      "p_home": 0.153,
      "p_draw": 0.213,
      "p_away": 0.633,
      "predictions": [
        {
          "score": "0:1",
          "points": "1.58"
        },
        {
          "score": "1:2",
          "points": "1.57"
        },
        {
          "score": "0:2",
          "points": "1.56"
        }
      ]
    },
    {
      "home": "Colombia",
      "away": "Congo DR",
      "kickoff": "Wed 24 Jun, 04:00",
      "day": "Tomorrow",
      "sort_key": "202606240400",
      "method": "market",
      "n_books": 1,
      "exp_goals_home": 1.79,
      "exp_goals_away": 0.78,
      "p_home": 0.601,
      "p_draw": 0.232,
      "p_away": 0.167,
      "predictions": [
        {
          "score": "1:0",
          "points": "1.59"
        },
        {
          "score": "2:1",
          "points": "1.53"
        },
        {
          "score": "2:0",
          "points": "1.50"
        }
      ]
    },
    {
      "home": "Switzerland",
      "away": "Canada",
      "kickoff": "Wed 24 Jun, 21:00",
      "day": "Tomorrow",
      "sort_key": "202606242100",
      "method": "market",
      "n_books": 1,
      "exp_goals_home": 1.43,
      "exp_goals_away": 1.27,
      "p_home": 0.396,
      "p_draw": 0.286,
      "p_away": 0.317,
      "predictions": [
        {
          "score": "1:0",
          "points": "1.09"
        },
        {
          "score": "2:1",
          "points": "1.07"
        },
        {
          "score": "3:2",
          "points": "1.02"
        }
      ]
    },
    {
      "home": "Bosnia and Herzegovina",
      "away": "Qatar",
      "kickoff": "Wed 24 Jun, 21:00",
      "day": "Tomorrow",
      "sort_key": "202606242100",
      "method": "market",
      "n_books": 1,
      "exp_goals_home": 2.32,
      "exp_goals_away": 0.95,
      "p_home": 0.666,
      "p_draw": 0.185,
      "p_away": 0.149,
      "predictions": [
        {
          "score": "1:0",
          "points": "1.65"
        },
        {
          "score": "2:1",
          "points": "1.64"
        },
        {
          "score": "2:0",
          "points": "1.62"
        }
      ]
    },
    {
      "home": "Scotland",
      "away": "Brazil",
      "kickoff": "Thu 25 Jun, 00:00",
      "day": "Day after",
      "sort_key": "202606250000",
      "method": "market",
      "n_books": 1,
      "exp_goals_home": 0.78,
      "exp_goals_away": 2.18,
      "p_home": 0.13,
      "p_draw": 0.191,
      "p_away": 0.679,
      "predictions": [
        {
          "score": "0:1",
          "points": "1.71"
        },
        {
          "score": "0:2",
          "points": "1.67"
        },
        {
          "score": "1:2",
          "points": "1.67"
        }
      ]
    },
    {
      "home": "Morocco",
      "away": "Haiti",
      "kickoff": "Thu 25 Jun, 00:00",
      "day": "Day after",
      "sort_key": "202606250000",
      "method": "market",
      "n_books": 1,
      "exp_goals_home": 2.77,
      "exp_goals_away": 0.61,
      "p_home": 0.796,
      "p_draw": 0.14,
      "p_away": 0.064,
      "predictions": [
        {
          "score": "2:0",
          "points": "1.93"
        },
        {
          "score": "3:0",
          "points": "1.88"
        },
        {
          "score": "1:0",
          "points": "1.88"
        }
      ]
    },
    {
      "home": "Czechia",
      "away": "Mexico",
      "kickoff": "Thu 25 Jun, 03:00",
      "day": "Day after",
      "sort_key": "202606250300",
      "method": "market",
      "n_books": 1,
      "exp_goals_home": 1.11,
      "exp_goals_away": 1.61,
      "p_home": 0.274,
      "p_draw": 0.238,
      "p_away": 0.487,
      "predictions": [
        {
          "score": "0:1",
          "points": "1.31"
        },
        {
          "score": "1:2",
          "points": "1.28"
        },
        {
          "score": "2:3",
          "points": "1.22"
        }
      ]
    },
    {
      "home": "South Africa",
      "away": "Korea Republic",
      "kickoff": "Thu 25 Jun, 03:00",
      "day": "Day after",
      "sort_key": "202606250300",
      "method": "market",
      "n_books": 1,
      "exp_goals_home": 0.93,
      "exp_goals_away": 1.83,
      "p_home": 0.189,
      "p_draw": 0.241,
      "p_away": 0.569,
      "predictions": [
        {
          "score": "0:1",
          "points": "1.49"
        },
        {
          "score": "1:2",
          "points": "1.46"
        },
        {
          "score": "0:2",
          "points": "1.41"
        }
      ]
    },
    {
      "home": "Ecuador",
      "away": "Germany",
      "kickoff": "Thu 25 Jun, 22:00",
      "day": "Day after",
      "sort_key": "202606252200",
      "method": "market",
      "n_books": 1,
      "exp_goals_home": 1.25,
      "exp_goals_away": 1.73,
      "p_home": 0.283,
      "p_draw": 0.232,
      "p_away": 0.485,
      "predictions": [
        {
          "score": "0:1",
          "points": "1.28"
        },
        {
          "score": "1:2",
          "points": "1.27"
        },
        {
          "score": "2:3",
          "points": "1.22"
        }
      ]
    },
    {
      "home": "Curacao",
      "away": "Ivory Coast",
      "kickoff": "Thu 25 Jun, 22:00",
      "day": "Day after",
      "sort_key": "202606252200",
      "method": "market",
      "n_books": 1,
      "exp_goals_home": 0.63,
      "exp_goals_away": 2.88,
      "p_home": 0.07,
      "p_draw": 0.125,
      "p_away": 0.806,
      "predictions": [
        {
          "score": "0:2",
          "points": "1.95"
        },
        {
          "score": "0:3",
          "points": "1.90"
        },
        {
          "score": "1:3",
          "points": "1.89"
        }
      ]
    }
  ]
}
